igtts.py
igtts-0.1.2.dist-info/LICENSE
igtts-0.1.2.dist-info/METADATA
igtts-0.1.2.dist-info/WHEEL
igtts-0.1.2.dist-info/entry_points.txt
igtts-0.1.2.dist-info/RECORD
