Metadata-Version: 2.3
Name: iGTTS
Version: 0.1.2
Summary: Gemini TTS CLI
License: MIT
Keywords: TTS,Gemini
Author: iChochy
Author-email: me@ichochy.com
Requires-Python: >=3.13
Classifier: License :: OSI Approved :: MIT License
Classifier: Programming Language :: Python :: 3
Classifier: Programming Language :: Python :: 3.13
Requires-Dist: google-genai (>=1.36.0,<2.0.0)
Project-URL: Homepage, https://tts.ichochy.com
